[
  {
    "id": 52736676409257984,
    "user_id": 214167672,
    "full_text": "RT @raffamoretti: Politicamente corretti: le regole di @internazionale http://t.co/ZwK5nAm",
    "created_at": "Tue Mar 29 14:19:38 +0000 2011"
  },
  {
    "id": 52719667395035137,
    "user_id": 214167672,
    "full_text": "@studioRES Razmišljam da prevedem i tog Pasolinija, ali ne znam smije li se prevoditi bez pitanja!! Malo me frka zbog autorskih prava i to!!",
    "created_at": "Tue Mar 29 13:12:02 +0000 2011"
  },
  {
    "id": 44336865276473344,
    "user_id": 214167672,
    "full_text": "Posquacchera rediviva: novi post na blogu: http://posquacchera.wordpress.com/2011/03/06/antijezik/",
    "created_at": "Sun Mar 06 10:01:47 +0000 2011"
  },
  {
    "id": 11076140152127489,
    "user_id": 214167672,
    "full_text": "@fraktura Je li to ona nagrada koju Nives Celzijus-Drpić nije dobila?",
    "created_at": "Sat Dec 04 15:15:32 +0000 2010"
  },
  {
    "id": 10640492773507072,
    "user_id": 214167672,
    "full_text": "@studioRES Dobro jutro, moja loša savjesti;)!!!!!",
    "created_at": "Fri Dec 03 10:24:25 +0000 2010"
  },
  {
    "id": 10082094306820097,
    "user_id": 214167672,
    "full_text": "I 'capo' i 'testa' su 'glava', ali reći ćemo 'capo di famiglia' (ne: 'testa') i 'perdere la testa' (ne: 'il capo').",
    "created_at": "Wed Dec 01 21:25:33 +0000 2010"
  },
  {
    "id": 10055027116740608,
    "user_id": 214167672,
    "full_text": "Određeni član ima svojstvo da izazove iščekivanje, i naslovima daje upečatljivost. [MP, RS]",
    "created_at": "Wed Dec 01 19:37:59 +0000 2010"
  },
  {
    "id": 10054147315343360,
    "user_id": 214167672,
    "full_text": "Ako gramatike kažu da se član izostavlja u naslovima knjiga, zašto onda \"Il nome della rosa\"?",
    "created_at": "Wed Dec 01 19:34:30 +0000 2010"
  },
  {
    "id": 7561879991877632,
    "user_id": 214167672,
    "full_text": "@studioRES Hehe, pratimo se!!! Dobri su ti glosariji!!!",
    "created_at": "Wed Nov 24 22:31:07 +0000 2010"
  },
  {
    "id": 6825131707998208,
    "user_id": 214167672,
    "full_text": "'Zampogna' (=gajde) i 'sinfonia' (=simfonija) imaju istu etimologiju (gr. sýn + phoné).",
    "created_at": "Mon Nov 22 21:43:32 +0000 2010"
  },
  {
    "id": 3584769094848512,
    "user_id": 214167672,
    "full_text": "Novi post na blogu: http://posquacchera.wordpress.com/2010/11/14/naglasci/",
    "created_at": "Sat Nov 13 23:07:30 +0000 2010"
  },
  {
    "id": 3546440521482242,
    "user_id": 214167672,
    "full_text": "Akronim za sedam smrtnih grijeha: saligia (superbia, avarizia, lussuria, ira, gola, invidia, accidia).",
    "created_at": "Sat Nov 13 20:35:11 +0000 2010"
  },
  {
    "id": 3332108349083648,
    "user_id": 214167672,
    "full_text": "Una lingua è un dialetto che ha fatto carriera. (Gaetano Berruto)",
    "created_at": "Sat Nov 13 06:23:31 +0000 2010"
  },
  {
    "id": 2460755156803585,
    "user_id": 214167672,
    "full_text": "Lakše je tvitati nego blogati...",
    "created_at": "Wed Nov 10 20:41:04 +0000 2010"
  }
]