[
  {
    "id": 698185151293992960,
    "user_id": 467503476,
    "full_text": "Be my valentine🙈 https://t.co/5xDwiS7iKe",
    "created_at": "Fri Feb 12 16:41:26 +0000 2016"
  },
  {
    "id": 689034966747840512,
    "user_id": 467503476,
    "full_text": "And every girl in here gotta look me up and down https://t.co/Wi4oiWoSev",
    "created_at": "Mon Jan 18 10:41:52 +0000 2016"
  },
  {
    "id": 642803340024356864,
    "user_id": 467503476,
    "full_text": "Bae🔐 #finally17 @ Rujanfest West Gate https://t.co/JCMYJLPGE5",
    "created_at": "Sat Sep 12 20:53:53 +0000 2015"
  },
  {
    "id": 642802866760065024,
    "user_id": 467503476,
    "full_text": "Bea #finally17 https://t.co/vQnHPNJfK6",
    "created_at": "Sat Sep 12 20:52:00 +0000 2015"
  },
  {
    "id": 633720387587690496,
    "user_id": 467503476,
    "full_text": "I'm done. https://t.co/kKaUn48prq",
    "created_at": "Tue Aug 18 19:21:29 +0000 2015"
  },
  {
    "id": 630151119881285632,
    "user_id": 467503476,
    "full_text": "'Gotovo se sve moze preboljeti.'-Greys Anatomy @ Prižba https://t.co/DkYmqddFbp",
    "created_at": "Sat Aug 08 22:58:29 +0000 2015"
  },
  {
    "id": 617078768952287233,
    "user_id": 467503476,
    "full_text": "Hey! I'm on #Kik - my username is 'laraajuretic' http://t.co/LMm4JMrUml http://t.co/odkjQs6NDJ",
    "created_at": "Fri Jul 03 21:13:37 +0000 2015"
  },
  {
    "id": 607560950749753344,
    "user_id": 467503476,
    "full_text": "Ojacali smo💪 https://t.co/SzhoIZKgae",
    "created_at": "Sun Jun 07 14:53:13 +0000 2015"
  },
  {
    "id": 594237292350480384,
    "user_id": 467503476,
    "full_text": "Vienna❤ @ Vienna https://t.co/n61UdwEzvn",
    "created_at": "Fri May 01 20:29:45 +0000 2015"
  },
  {
    "id": 594236557269323777,
    "user_id": 467503476,
    "full_text": "Vienna❤ https://t.co/CiykYHnKIj",
    "created_at": "Fri May 01 20:26:50 +0000 2015"
  },
  {
    "id": 592366079730700289,
    "user_id": 467503476,
    "full_text": "Good moments in present often become great moments in history. https://t.co/7FfOgMpqNK",
    "created_at": "Sun Apr 26 16:34:13 +0000 2015"
  },
  {
    "id": 560875855317311490,
    "user_id": 467503476,
    "full_text": "#tbt with ingrid_burazer &amp; mauricija.bolfek http://t.co/2rBSgvxAOp",
    "created_at": "Thu Jan 29 19:03:19 +0000 2015"
  },
  {
    "id": 550774832921841664,
    "user_id": 467503476,
    "full_text": "2015🎊🎉👌❄ http://t.co/RMhPhOih5t",
    "created_at": "Thu Jan 01 22:05:27 +0000 2015"
  },
  {
    "id": 547898036475543552,
    "user_id": 467503476,
    "full_text": "12/23/14 @ Bunga Bunga http://t.co/W5VVnx6NIu",
    "created_at": "Wed Dec 24 23:34:06 +0000 2014"
  },
  {
    "id": 547896055346765824,
    "user_id": 467503476,
    "full_text": "Just posted a photo @ Bunga Bunga http://t.co/f7d9PPdxGz",
    "created_at": "Wed Dec 24 23:26:13 +0000 2014"
  },
  {
    "id": 547149715469787136,
    "user_id": 467503476,
    "full_text": "@Cukarinka heeej tek sam sada prvi put dosla na twitter. Pozdrav :-)",
    "created_at": "Mon Dec 22 22:00:32 +0000 2014"
  },
  {
    "id": 541627598452060160,
    "user_id": 467503476,
    "full_text": "“I just want somebody who will never stop choosing me.” http://t.co/FXGfq5TYuT",
    "created_at": "Sun Dec 07 16:17:37 +0000 2014"
  },
  {
    "id": 541618464692371457,
    "user_id": 467503476,
    "full_text": "Maybe we'll meet again,when we are slightly older and our minds less hectic, and I'll be right for you… http://t.co/O4iXLoyKu7",
    "created_at": "Sun Dec 07 15:41:19 +0000 2014"
  },
  {
    "id": 507679672453578752,
    "user_id": 467503476,
    "full_text": "BIEBER OR DIE! Still #Belieber after 3 years. #BieberFever is still in Croatia",
    "created_at": "Fri Sep 05 00:00:40 +0000 2014"
  },
  {
    "id": 507678753737412608,
    "user_id": 467503476,
    "full_text": "RT @monikakralj: @KianLawley sweetie happy birthday! Wish u all best cuz u deserve it!! 🎉🎊🎁🎈💝👻💋",
    "created_at": "Thu Sep 04 23:57:01 +0000 2014"
  },
  {
    "id": 495323320846651392,
    "user_id": 467503476,
    "full_text": "#tbt #summer2013 http://t.co/wwG6gsPV4Z",
    "created_at": "Fri Aug 01 21:40:57 +0000 2014"
  },
  {
    "id": 484845712795271169,
    "user_id": 467503476,
    "full_text": "RT @justinbieber: People are going to say what they want about u. It happens. Sometimes u lose your cool. But be kind. Know your heart :) t…",
    "created_at": "Thu Jul 03 23:46:40 +0000 2014"
  },
  {
    "id": 484800058970615808,
    "user_id": 467503476,
    "full_text": "\"I don’t love him but he’s here and you aren’t.\" #MD http://t.co/A174GwUGj0",
    "created_at": "Thu Jul 03 20:45:15 +0000 2014"
  },
  {
    "id": 479359484909715456,
    "user_id": 467503476,
    "full_text": "'If you dance with your heart, your body will follow.' -Mia Michaels❤👯❤ http://t.co/qRXEC9yVo3",
    "created_at": "Wed Jun 18 20:26:21 +0000 2014"
  },
  {
    "id": 475015048658960384,
    "user_id": 467503476,
    "full_text": "We don't eat calories, we eat food. 🐷🍰🍗🍔🍟🍕 @monikakralj nay http://t.co/uPxpqPAlHW",
    "created_at": "Fri Jun 06 20:43:07 +0000 2014"
  },
  {
    "id": 473569374016524288,
    "user_id": 467503476,
    "full_text": "Momiii moja najdrazaaa. Sretan ti 16-ti rodendan i sve najnajnajbolje! Ne zelim sad pisat neki dugi… http://t.co/m3t3Yu2dpt",
    "created_at": "Mon Jun 02 20:58:31 +0000 2014"
  },
  {
    "id": 469541129458032640,
    "user_id": 467503476,
    "full_text": "Just posted a photo @ na brodicu http://t.co/5jcnesFJt5",
    "created_at": "Thu May 22 18:11:43 +0000 2014"
  },
  {
    "id": 467739974256066561,
    "user_id": 467503476,
    "full_text": "As soon as you stop wanting something, you get it. http://t.co/Ac4vjkojJh",
    "created_at": "Sat May 17 18:54:34 +0000 2014"
  },
  {
    "id": 464129155638898688,
    "user_id": 467503476,
    "full_text": "#proud http://t.co/PCZMrUka0r",
    "created_at": "Wed May 07 19:46:28 +0000 2014"
  },
  {
    "id": 463062206087962624,
    "user_id": 467503476,
    "full_text": "Sick😷 but my love is here #DylanObrien @ Teen Wolf http://t.co/p1VSreDTZb",
    "created_at": "Sun May 04 21:06:47 +0000 2014"
  },
  {
    "id": 458979582247723009,
    "user_id": 467503476,
    "full_text": "“The hardest thing is not talking to someone you used to talk to everyday” http://t.co/BAyNpmlmS4",
    "created_at": "Wed Apr 23 14:43:54 +0000 2014"
  },
  {
    "id": 453285124592128000,
    "user_id": 467503476,
    "full_text": "@justinbieber you are the best. I love you shawty. Stay cool and swaggie like you always are",
    "created_at": "Mon Apr 07 21:36:09 +0000 2014"
  },
  {
    "id": 447805386884927489,
    "user_id": 467503476,
    "full_text": "Slikamo se samo dok ima sunca.... lea_rivic 🌅🌞☀😘 @ VII. Gimnazija http://t.co/SlNpksYXpX",
    "created_at": "Sun Mar 23 18:41:38 +0000 2014"
  },
  {
    "id": 445198437957779458,
    "user_id": 467503476,
    "full_text": "'Zo, you can't change the past.'-Heath #ahouseofnightnovel #burned http://t.co/id1KnYENTM",
    "created_at": "Sun Mar 16 14:02:33 +0000 2014"
  },
  {
    "id": 444973054603845632,
    "user_id": 467503476,
    "full_text": "'Prošlost ne možeš promijeniti.'-Heath #ahouseofnightnovel #Burned http://t.co/dEdSJtZFNc",
    "created_at": "Sat Mar 15 23:06:58 +0000 2014"
  },
  {
    "id": 440179189896204288,
    "user_id": 467503476,
    "full_text": "RT @carlyraejepsen: Happy Birthday to YOU @justinbieber !!! http://t.co/xRtwsVcTbB",
    "created_at": "Sun Mar 02 17:37:51 +0000 2014"
  },
  {
    "id": 440179012892393473,
    "user_id": 467503476,
    "full_text": "RT @JeremyBieber: Happy Birthday son. Wow 20!",
    "created_at": "Sun Mar 02 17:37:09 +0000 2014"
  },
  {
    "id": 440178987659444224,
    "user_id": 467503476,
    "full_text": "RT @pattiemallette: Happy Birthday YOU KNOW WHO! I love you. Xoxo",
    "created_at": "Sun Mar 02 17:37:03 +0000 2014"
  },
  {
    "id": 440178777604497408,
    "user_id": 467503476,
    "full_text": "RT @justinbieber: Thanks to everyone for all the birthday wishes. Means a lot. Blessed and hoping we can continue to change the world toget…",
    "created_at": "Sun Mar 02 17:36:13 +0000 2014"
  },
  {
    "id": 439537345160044545,
    "user_id": 467503476,
    "full_text": "'You won't be 16 forever' -Usher and now he's turning 20. Omg that's so wierd. He's not teen anymore.… http://t.co/rUYAFbeb9U",
    "created_at": "Fri Feb 28 23:07:23 +0000 2014"
  },
  {
    "id": 439526718639185920,
    "user_id": 467503476,
    "full_text": "Najbolji puni 20 godina. Vec.. A u kurac. Happy birthday @justinbieber #loveyou #happybirthday… http://t.co/mGlOakSCFl",
    "created_at": "Fri Feb 28 22:25:10 +0000 2014"
  },
  {
    "id": 439511441201455104,
    "user_id": 467503476,
    "full_text": "#20ReasonsWhyWeLoveJustin ***I have a thuosand reasons",
    "created_at": "Fri Feb 28 21:24:27 +0000 2014"
  },
  {
    "id": 439511174703771648,
    "user_id": 467503476,
    "full_text": "#20ReasonsWhyWeLoveJustin I love you, you love me..",
    "created_at": "Fri Feb 28 21:23:24 +0000 2014"
  },
  {
    "id": 439511099323744256,
    "user_id": 467503476,
    "full_text": "#20ReasonsWhyWeLoveJustin #Belieber4ever",
    "created_at": "Fri Feb 28 21:23:06 +0000 2014"
  },
  {
    "id": 439511032747540480,
    "user_id": 467503476,
    "full_text": "#20ReasonsWhyWeLoveJustin @justinbieber Ly",
    "created_at": "Fri Feb 28 21:22:50 +0000 2014"
  },
  {
    "id": 439510975495274496,
    "user_id": 467503476,
    "full_text": "#20ReasonsWhyWeLoveJustin",
    "created_at": "Fri Feb 28 21:22:36 +0000 2014"
  },
  {
    "id": 439507807449415680,
    "user_id": 467503476,
    "full_text": "@justinbieber Happy birthday! I love you so much that I can't explan.. I know that you won't see this.. #youarethebest",
    "created_at": "Fri Feb 28 21:10:01 +0000 2014"
  },
  {
    "id": 439506519923916800,
    "user_id": 467503476,
    "full_text": "@monikakralj pljesak za mene *PLJESAK*",
    "created_at": "Fri Feb 28 21:04:54 +0000 2014"
  },
  {
    "id": 439505883161460736,
    "user_id": 467503476,
    "full_text": "Starting from march first this year, the media won't say ''teenage popstar Justin Bieber'' anymore. \n\nOh shit...",
    "created_at": "Fri Feb 28 21:02:22 +0000 2014"
  },
  {
    "id": 439505714089054208,
    "user_id": 467503476,
    "full_text": "@monikakralj OMG AHHAHAHAHHAHHAHHAHAHAHHAHAHAHAHAHHAHAHAHAHAHAHAH TEK SAD VIDIM OD KAD JE TO JER MI SE RAZGOVOR NIJE CIJELI PRIKAZAO HAHAHAH",
    "created_at": "Fri Feb 28 21:01:42 +0000 2014"
  },
  {
    "id": 439504907276914689,
    "user_id": 467503476,
    "full_text": "RT @VEVO: .@justinbieber's \"Baby\" has reached 1 BILLION views! Congratulations to Justin &amp; of course the fans! http://t.co/LEsrZoXeES #Baby…",
    "created_at": "Fri Feb 28 20:58:30 +0000 2014"
  },
  {
    "id": 439504845050232833,
    "user_id": 467503476,
    "full_text": "RT @justinbieber: me, my team, and my beliebers we are focused on the music. that is what matters. much love to everybody",
    "created_at": "Fri Feb 28 20:58:15 +0000 2014"
  },
  {
    "id": 439504154776854528,
    "user_id": 467503476,
    "full_text": "@justinbieber I love you so much.. I haven't been so much on twitter this few days but i can't forget your 20th birthday! #HappyBirthday",
    "created_at": "Fri Feb 28 20:55:30 +0000 2014"
  },
  {
    "id": 439503263369805824,
    "user_id": 467503476,
    "full_text": "@monikakralj a ljubaviiiiiiiiiiiiiiii nisam bila uopce na twitteru &lt;3&lt;3&lt;3&lt;3&lt;3",
    "created_at": "Fri Feb 28 20:51:58 +0000 2014"
  },
  {
    "id": 439440928475193344,
    "user_id": 467503476,
    "full_text": "Just posted a photo http://t.co/sBGl2bgIgZ",
    "created_at": "Fri Feb 28 16:44:16 +0000 2014"
  },
  {
    "id": 439152648449953792,
    "user_id": 467503476,
    "full_text": "Just posted a photo http://t.co/igjgM7jXVr",
    "created_at": "Thu Feb 27 21:38:45 +0000 2014"
  },
  {
    "id": 435552550650413056,
    "user_id": 467503476,
    "full_text": "U elemeentu👌💃💪👯👏 @ Zagrebački Velesajam http://t.co/BK3nWkwRAG",
    "created_at": "Mon Feb 17 23:13:14 +0000 2014"
  },
  {
    "id": 435135332737359873,
    "user_id": 467503476,
    "full_text": "Can't you see you belong with me👌😍🙊💋 http://t.co/LF9BwZTAXW",
    "created_at": "Sun Feb 16 19:35:22 +0000 2014"
  },
  {
    "id": 433010938686746626,
    "user_id": 467503476,
    "full_text": "Best crew ever!👌👯 PS Escape💜 #kingsofstyle #hiphop @ Zagrebački Velesajam http://t.co/rYWkUYD49C",
    "created_at": "Mon Feb 10 22:53:47 +0000 2014"
  },
  {
    "id": 428535846326009856,
    "user_id": 467503476,
    "full_text": "'Wear the pants, don't let the pants wear you!' 25.01.2014. #believe #movie #belieber #bestidolever… http://t.co/WJMrqbFr4c",
    "created_at": "Wed Jan 29 14:31:22 +0000 2014"
  },
  {
    "id": 428296786714042368,
    "user_id": 467503476,
    "full_text": "Subota, gledanje filma, plakanje, prisjecanje koncerta, uzivancija! #justinbieber #believe #movie… http://t.co/xBAOfdkmoY",
    "created_at": "Tue Jan 28 22:41:25 +0000 2014"
  },
  {
    "id": 424674439364902912,
    "user_id": 467503476,
    "full_text": "Just posted a photo http://t.co/tFiA956KrD",
    "created_at": "Sat Jan 18 22:47:31 +0000 2014"
  },
  {
    "id": 422450128436621312,
    "user_id": 467503476,
    "full_text": "Kad vama nes treba, Lara je tu. A kad Lari nes treba nikog nema. Ma odite svi u kurac @ The Cookie… http://t.co/f6udGG5sxh",
    "created_at": "Sun Jan 12 19:28:54 +0000 2014"
  },
  {
    "id": 422153989011296256,
    "user_id": 467503476,
    "full_text": "RT @IslandRecords: .@JustinBieber #Journals | http://t.co/Drl0r0vi28",
    "created_at": "Sat Jan 11 23:52:08 +0000 2014"
  },
  {
    "id": 422153729664507904,
    "user_id": 467503476,
    "full_text": "#ExaBeliebers",
    "created_at": "Sat Jan 11 23:51:07 +0000 2014"
  },
  {
    "id": 421381896405139456,
    "user_id": 467503476,
    "full_text": "@justinbieber she's confident..ohh nono #followmeitsjaybeehere @itsjaybeehere",
    "created_at": "Thu Jan 09 20:44:07 +0000 2014"
  },
  {
    "id": 421381170035560448,
    "user_id": 467503476,
    "full_text": "@justinbieber @itsjaybeehere love me love meee say that you love me #followmeitsjaybeehere",
    "created_at": "Thu Jan 09 20:41:14 +0000 2014"
  },
  {
    "id": 421381112967860224,
    "user_id": 467503476,
    "full_text": "@itsjaybeehere #followmeitsjaybeehere love is in the aiiiiiiiir",
    "created_at": "Thu Jan 09 20:41:00 +0000 2014"
  },
  {
    "id": 421380947553300480,
    "user_id": 467503476,
    "full_text": "RT @justinbieber: live your dream. be creative",
    "created_at": "Thu Jan 09 20:40:21 +0000 2014"
  },
  {
    "id": 421380918213754882,
    "user_id": 467503476,
    "full_text": "@justinbieber @itsjaybeehere I think its time to you follow me finally #followmeitsjaybeehere",
    "created_at": "Thu Jan 09 20:40:14 +0000 2014"
  },
  {
    "id": 421380672041648128,
    "user_id": 467503476,
    "full_text": "@itsjaybeehere Soo call me maybe? #followmeitsjaybeehere",
    "created_at": "Thu Jan 09 20:39:15 +0000 2014"
  },
  {
    "id": 421380409352409088,
    "user_id": 467503476,
    "full_text": "@itsjaybeehere Belieber4ever. Cant describe how much i love you #followmeitsjaybeehere",
    "created_at": "Thu Jan 09 20:38:13 +0000 2014"
  },
  {
    "id": 421380284043390976,
    "user_id": 467503476,
    "full_text": "@itsjaybeehere Aaaaa please. Love you #followmeitsjaybeehere",
    "created_at": "Thu Jan 09 20:37:43 +0000 2014"
  },
  {
    "id": 421380201835024384,
    "user_id": 467503476,
    "full_text": "@itsjaybeehere I knew it. You will never follow me or something #followmeitsjaybeehere",
    "created_at": "Thu Jan 09 20:37:23 +0000 2014"
  },
  {
    "id": 421380061724307456,
    "user_id": 467503476,
    "full_text": "@itsjaybeehere I would be thankfull if you could just press one little button #followmeitsjaybeehere",
    "created_at": "Thu Jan 09 20:36:50 +0000 2014"
  },
  {
    "id": 421379833885491201,
    "user_id": 467503476,
    "full_text": "@itsjaybeehere #followmeitsjaybeehere#followmeitsjaybeehere#followmeitsjaybeehere#followmeitsjaybeehere#followmeitsjaybeehere hohooo",
    "created_at": "Thu Jan 09 20:35:55 +0000 2014"
  },
  {
    "id": 421379692604575745,
    "user_id": 467503476,
    "full_text": "@itsjaybeehere cmmon Juss #followmeitsjaybeehere",
    "created_at": "Thu Jan 09 20:35:22 +0000 2014"
  },
  {
    "id": 421379521342734336,
    "user_id": 467503476,
    "full_text": "@itsjaybeehere follow me please #followmeitsjaybeehere my mum told me that if I would be nice I will get anythiung what I want sooo",
    "created_at": "Thu Jan 09 20:34:41 +0000 2014"
  },
  {
    "id": 421379080403972096,
    "user_id": 467503476,
    "full_text": "@itsjaybeehere I've missed you live stream and I cant believe how sad I am #followmeitsjaybeehere",
    "created_at": "Thu Jan 09 20:32:56 +0000 2014"
  },
  {
    "id": 421378793077370880,
    "user_id": 467503476,
    "full_text": "@itsjaybeehere Whaaaaaat now? @rihanna #followmeitsjaybeehere",
    "created_at": "Thu Jan 09 20:31:47 +0000 2014"
  },
  {
    "id": 421378680569356288,
    "user_id": 467503476,
    "full_text": "@itsjaybeehere I wish that you could only rt me",
    "created_at": "Thu Jan 09 20:31:20 +0000 2014"
  },
  {
    "id": 421378469272891392,
    "user_id": 467503476,
    "full_text": "@itsjaybeehere can you follow me? No? Ohh. Ok..",
    "created_at": "Thu Jan 09 20:30:30 +0000 2014"
  },
  {
    "id": 421378388649971712,
    "user_id": 467503476,
    "full_text": "@itsjaybeehere #followmeitsjaybeehere boooook",
    "created_at": "Thu Jan 09 20:30:11 +0000 2014"
  },
  {
    "id": 421378330961530880,
    "user_id": 467503476,
    "full_text": "@itsjaybeehere why dont you notice me?",
    "created_at": "Thu Jan 09 20:29:57 +0000 2014"
  },
  {
    "id": 421378170319679488,
    "user_id": 467503476,
    "full_text": "@itsjaybeehere I'm dying here.. and by the way I dont know english so well",
    "created_at": "Thu Jan 09 20:29:19 +0000 2014"
  },
  {
    "id": 421377999225630720,
    "user_id": 467503476,
    "full_text": "@itsjaybeehere I knew it..you dont love me.. #followmeitsjaybeehere",
    "created_at": "Thu Jan 09 20:28:38 +0000 2014"
  },
  {
    "id": 421377902752440321,
    "user_id": 467503476,
    "full_text": "@itsjaybeehere Wut wut wut wut #followmeitsjaybeehere",
    "created_at": "Thu Jan 09 20:28:15 +0000 2014"
  },
  {
    "id": 421377844195766272,
    "user_id": 467503476,
    "full_text": "@itsjaybeehere Heeeeey sexy boy #followmeitsjaybeehere",
    "created_at": "Thu Jan 09 20:28:01 +0000 2014"
  },
  {
    "id": 421377687681130496,
    "user_id": 467503476,
    "full_text": "@itsjaybeehere You would follow me if you really love me.. :(",
    "created_at": "Thu Jan 09 20:27:24 +0000 2014"
  },
  {
    "id": 421377587621814272,
    "user_id": 467503476,
    "full_text": "@itsjaybeehere You will follow me if you really love me...",
    "created_at": "Thu Jan 09 20:27:00 +0000 2014"
  },
  {
    "id": 421377447636893697,
    "user_id": 467503476,
    "full_text": "@itsjaybeehere Pls follow me",
    "created_at": "Thu Jan 09 20:26:26 +0000 2014"
  },
  {
    "id": 421377401243705344,
    "user_id": 467503476,
    "full_text": "@itsjaybeehere or should I say OMB haha",
    "created_at": "Thu Jan 09 20:26:15 +0000 2014"
  },
  {
    "id": 421377350035451904,
    "user_id": 467503476,
    "full_text": "@itsjaybeehere  #followmeitsjaybeehere OMG notice meee",
    "created_at": "Thu Jan 09 20:26:03 +0000 2014"
  },
  {
    "id": 421377191054540801,
    "user_id": 467503476,
    "full_text": "#followmeitsjaybeehere pleaseee",
    "created_at": "Thu Jan 09 20:25:25 +0000 2014"
  },
  {
    "id": 421376905174999040,
    "user_id": 467503476,
    "full_text": "@itsjaybeehere  #followmeitsjaybeehere Choose meeeeeee!!",
    "created_at": "Thu Jan 09 20:24:17 +0000 2014"
  },
  {
    "id": 421376849189408769,
    "user_id": 467503476,
    "full_text": "@itsjaybeehere  #followmeitsjaybeehere :-)",
    "created_at": "Thu Jan 09 20:24:04 +0000 2014"
  },
  {
    "id": 421376384401829889,
    "user_id": 467503476,
    "full_text": "#followmeitsjaybeehere",
    "created_at": "Thu Jan 09 20:22:13 +0000 2014"
  },
  {
    "id": 411978375939362816,
    "user_id": 467503476,
    "full_text": "@JesseMcCartney Follow me please.. I just have wached your movie..Keith..YOu're fantastic. Love you",
    "created_at": "Sat Dec 14 21:57:53 +0000 2013"
  },
  {
    "id": 411977280408526849,
    "user_id": 467503476,
    "full_text": "RT @JesseMcCartney: Just finished up my interview at @ETonlineAlert. Airing soon! #InTechnicolorPart1 http://t.co/gOq8QYkYXo",
    "created_at": "Sat Dec 14 21:53:32 +0000 2013"
  },
  {
    "id": 400758564371066880,
    "user_id": 467503476,
    "full_text": "RT @justinbieber: this is what it is all about. never say never and believe ;) http://t.co/plZqlpY1O6",
    "created_at": "Wed Nov 13 22:54:22 +0000 2013"
  },
  {
    "id": 400758439703740416,
    "user_id": 467503476,
    "full_text": "RT @justinbieber: My dancers are hilarious! Pre show warm ups. Chile thank you for an incredible show! Te amo. http://t.co/yeAhhE6Coo",
    "created_at": "Wed Nov 13 22:53:52 +0000 2013"
  },
  {
    "id": 400758336905543680,
    "user_id": 467503476,
    "full_text": "RT @justinbieber: Beliebers got something special for u today, the #BelieveMoviePoster debut! But you’re going to have to work for it. Foll…",
    "created_at": "Wed Nov 13 22:53:27 +0000 2013"
  },
  {
    "id": 400757761769627648,
    "user_id": 467503476,
    "full_text": "Believe Movie #cantwait so excited @justinbieber hope you'll notice me @jonmchu why Believe movie cant be able sooner? Why? Hhhh",
    "created_at": "Wed Nov 13 22:51:10 +0000 2013"
  },
  {
    "id": 400756974029389824,
    "user_id": 467503476,
    "full_text": "RT @jonmchu: Oh yeah. This Christmas. My 5th movie... say what u want about him but when u see the movie, you'll hear the truth... http://t…",
    "created_at": "Wed Nov 13 22:48:02 +0000 2013"
  },
  {
    "id": 397080055920087040,
    "user_id": 467503476,
    "full_text": "@Sandric52 Um ok?",
    "created_at": "Sun Nov 03 19:17:17 +0000 2013"
  },
  {
    "id": 397073450319499264,
    "user_id": 467503476,
    "full_text": "I'm using this for the first time and I'm confused",
    "created_at": "Sun Nov 03 18:51:02 +0000 2013"
  },
  {
    "id": 391335148467535873,
    "user_id": 467503476,
    "full_text": "\"Your idol can save your life, but you can't save your idol's life\"",
    "created_at": "Fri Oct 18 22:49:04 +0000 2013"
  },
  {
    "id": 391334352468328449,
    "user_id": 467503476,
    "full_text": "Justin is the hardest working boy I know. He does so much for us. He is so passionate about what he does and about the music he creates.",
    "created_at": "Fri Oct 18 22:45:54 +0000 2013"
  },
  {
    "id": 391333868722462720,
    "user_id": 467503476,
    "full_text": "I love being different and crazy... But only in the darkness of my fuckin room 👽🙊🙉✌💤🙅",
    "created_at": "Fri Oct 18 22:43:59 +0000 2013"
  },
  {
    "id": 389061276875620352,
    "user_id": 467503476,
    "full_text": "Gossiping with friends @monikakralj &amp; Saraa at #Ritamgrada in Zagreb http://t.co/CEDlNEYmI7",
    "created_at": "Sat Oct 12 16:13:31 +0000 2013"
  },
  {
    "id": 387249560206053376,
    "user_id": 467503476,
    "full_text": "RT @scooterbraun: @justinbieber #heartbreaker is #1 in 52 countries and counting. #MusicMondays",
    "created_at": "Mon Oct 07 16:14:24 +0000 2013"
  },
  {
    "id": 387248557960331264,
    "user_id": 467503476,
    "full_text": "RT @luke_brooks: I couldn't give a fuck how famous someone is. Family comes first. We were  raised with not much and we'll be happy to leav…",
    "created_at": "Mon Oct 07 16:10:25 +0000 2013"
  },
  {
    "id": 387248392985772032,
    "user_id": 467503476,
    "full_text": "RT @Adzlegends: BELIEBERS WE'VE SUCCEEDED http://t.co/XkFOw2ij25",
    "created_at": "Mon Oct 07 16:09:46 +0000 2013"
  },
  {
    "id": 387248260286402560,
    "user_id": 467503476,
    "full_text": "RT @jwaterboy12: Yup. I just paid money for a Justin Bieber song. I actually like his music. #NoHomo http://t.co/zEpBSJtPhf",
    "created_at": "Mon Oct 07 16:09:14 +0000 2013"
  },
  {
    "id": 387247450773143552,
    "user_id": 467503476,
    "full_text": "R.I.P. Soon \nSorrynotsorry",
    "created_at": "Mon Oct 07 16:06:01 +0000 2013"
  },
  {
    "id": 387246806477721600,
    "user_id": 467503476,
    "full_text": "SOON IS NOW!\nThanks God. It was time... but it worth it to wait for the song. @justinbieber love you men :)",
    "created_at": "Mon Oct 07 16:03:28 +0000 2013"
  },
  {
    "id": 387246451039797248,
    "user_id": 467503476,
    "full_text": "RT @dankanter: Soon just got a lot sooner.",
    "created_at": "Mon Oct 07 16:02:03 +0000 2013"
  },
  {
    "id": 387246139373658113,
    "user_id": 467503476,
    "full_text": "RT @justinbieber: maybe u might get lucky with two songs in a week",
    "created_at": "Mon Oct 07 16:00:49 +0000 2013"
  },
  {
    "id": 387245321656360961,
    "user_id": 467503476,
    "full_text": "WE DID IT! http://t.co/I4brwHP5g5",
    "created_at": "Mon Oct 07 15:57:34 +0000 2013"
  },
  {
    "id": 387244269783613441,
    "user_id": 467503476,
    "full_text": "Justin I'm in love with your new song. #Heartbreaker is amazing and soon you'll find your real love. xoxo",
    "created_at": "Mon Oct 07 15:53:23 +0000 2013"
  },
  {
    "id": 382937458784354304,
    "user_id": 467503476,
    "full_text": "@mellythemonkey @SarraLovesBieb fml",
    "created_at": "Wed Sep 25 18:39:39 +0000 2013"
  },
  {
    "id": 382937271898767360,
    "user_id": 467503476,
    "full_text": "@mellythemonkey pleaseeeeee #mellyfollowspree follow me. This is so unfair",
    "created_at": "Wed Sep 25 18:38:54 +0000 2013"
  },
  {
    "id": 382937102331445248,
    "user_id": 467503476,
    "full_text": "@mellythemonkey yes. And i think you should follow me",
    "created_at": "Wed Sep 25 18:38:14 +0000 2013"
  },
  {
    "id": 382931974757031937,
    "user_id": 467503476,
    "full_text": "#mellyfollowspree ohhh",
    "created_at": "Wed Sep 25 18:17:51 +0000 2013"
  },
  {
    "id": 382931811346952192,
    "user_id": 467503476,
    "full_text": "RT @justinbieber: This is insane. It all started with this youtube page www.youtube.com/justinbieber and now I have an Album coming 2morrow…",
    "created_at": "Wed Sep 25 18:17:13 +0000 2013"
  },
  {
    "id": 382931633877569537,
    "user_id": 467503476,
    "full_text": "#mellyfollowspree Melly what are you doing?? You supose to follow me..",
    "created_at": "Wed Sep 25 18:16:30 +0000 2013"
  },
  {
    "id": 382931224056315904,
    "user_id": 467503476,
    "full_text": "@mellythemonkey i think that you dont follow the pepole. Am I right? #mellyfollowspree",
    "created_at": "Wed Sep 25 18:14:52 +0000 2013"
  },
  {
    "id": 382930620810534912,
    "user_id": 467503476,
    "full_text": "@mellythemonkey #mellyfollowspree ohh you pervvv i like you",
    "created_at": "Wed Sep 25 18:12:29 +0000 2013"
  },
  {
    "id": 382930449389326336,
    "user_id": 467503476,
    "full_text": "RT @justinbieber: I'm at ihop about to mow down some pancakes :p",
    "created_at": "Wed Sep 25 18:11:48 +0000 2013"
  },
  {
    "id": 382930405110079488,
    "user_id": 467503476,
    "full_text": "#mellyfollowspree why dont you just follow me so i can study in peace",
    "created_at": "Wed Sep 25 18:11:37 +0000 2013"
  },
  {
    "id": 382930207575134208,
    "user_id": 467503476,
    "full_text": "#mellyfollowspree @mellythemonkey follow me follow me",
    "created_at": "Wed Sep 25 18:10:50 +0000 2013"
  },
  {
    "id": 382929636940079104,
    "user_id": 467503476,
    "full_text": "#mellyfollowspree why ohh why I love youuuuu",
    "created_at": "Wed Sep 25 18:08:34 +0000 2013"
  },
  {
    "id": 382929395629166592,
    "user_id": 467503476,
    "full_text": "#mellyfollowspree supraaaaa",
    "created_at": "Wed Sep 25 18:07:37 +0000 2013"
  },
  {
    "id": 382929309935370240,
    "user_id": 467503476,
    "full_text": "#mellyfollowspree wuut",
    "created_at": "Wed Sep 25 18:07:16 +0000 2013"
  },
  {
    "id": 382929249239597056,
    "user_id": 467503476,
    "full_text": "#mellyfollowspree",
    "created_at": "Wed Sep 25 18:07:02 +0000 2013"
  },
  {
    "id": 382929176246124544,
    "user_id": 467503476,
    "full_text": "@mellythemonkey #mellyfollowspree :-)",
    "created_at": "Wed Sep 25 18:06:44 +0000 2013"
  },
  {
    "id": 382929086982926336,
    "user_id": 467503476,
    "full_text": "@mellythemonkey #mellyfollowspree",
    "created_at": "Wed Sep 25 18:06:23 +0000 2013"
  },
  {
    "id": 382929026266185728,
    "user_id": 467503476,
    "full_text": "@mellythemonkey",
    "created_at": "Wed Sep 25 18:06:09 +0000 2013"
  },
  {
    "id": 382555419996348417,
    "user_id": 467503476,
    "full_text": "RT @mellythemonkey: your word is a lamp for my feet, a light on my path.",
    "created_at": "Tue Sep 24 17:21:34 +0000 2013"
  },
  {
    "id": 382256074499555328,
    "user_id": 467503476,
    "full_text": "RT @justinbieber: I love monkeys",
    "created_at": "Mon Sep 23 21:32:04 +0000 2013"
  },
  {
    "id": 382253249308667905,
    "user_id": 467503476,
    "full_text": "#imagine Justin shouting your name and collapsing on top of you as he climaxes, sweaty and breathing hard.",
    "created_at": "Mon Sep 23 21:20:51 +0000 2013"
  },
  {
    "id": 382253026758885376,
    "user_id": 467503476,
    "full_text": "I just spent my whole day in study and now I dont know nothing. How can this happend? Fml",
    "created_at": "Mon Sep 23 21:19:58 +0000 2013"
  },
  {
    "id": 382206618894868480,
    "user_id": 467503476,
    "full_text": "RT @mellythemonkey: i love you all",
    "created_at": "Mon Sep 23 18:15:33 +0000 2013"
  },
  {
    "id": 382196531639894016,
    "user_id": 467503476,
    "full_text": "Nothing's fine... I'm torn. #onedirection",
    "created_at": "Mon Sep 23 17:35:28 +0000 2013"
  },
  {
    "id": 382192532492656640,
    "user_id": 467503476,
    "full_text": "Justin I'm your girl, not Rihanna. Get it?",
    "created_at": "Mon Sep 23 17:19:35 +0000 2013"
  },
  {
    "id": 382192227101208576,
    "user_id": 467503476,
    "full_text": "RT @justinbieber: Watched my girl @rihanna kill it last night in Singapore. Tomorrow it is my turn. #BELIEVETOUR",
    "created_at": "Mon Sep 23 17:18:22 +0000 2013"
  },
  {
    "id": 382192137775104001,
    "user_id": 467503476,
    "full_text": "RT @justinbieber: It begins",
    "created_at": "Mon Sep 23 17:18:01 +0000 2013"
  },
  {
    "id": 382192059618430976,
    "user_id": 467503476,
    "full_text": "RT @justinbieber: love my boys. lol http://t.co/1DGysJbQld",
    "created_at": "Mon Sep 23 17:17:42 +0000 2013"
  },
  {
    "id": 382191584504479744,
    "user_id": 467503476,
    "full_text": "RT @NickDeMoura: @justinbieber killed it tonight! http://t.co/a7lglAuzmN",
    "created_at": "Mon Sep 23 17:15:49 +0000 2013"
  },
  {
    "id": 382191535439478785,
    "user_id": 467503476,
    "full_text": "RT @justinbieber: @thatrygood welcome back",
    "created_at": "Mon Sep 23 17:15:37 +0000 2013"
  },
  {
    "id": 382191414270234624,
    "user_id": 467503476,
    "full_text": "RT @justinbieber: @bieberarmy i look like im yelling at myself. lol",
    "created_at": "Mon Sep 23 17:15:08 +0000 2013"
  },
  {
    "id": 379329362296078337,
    "user_id": 467503476,
    "full_text": "RT @mellythemonkey: #believemovie believe dance tour http://t.co/jkPFkWIPdA",
    "created_at": "Sun Sep 15 19:42:22 +0000 2013"
  },
  {
    "id": 378147800287952896,
    "user_id": 467503476,
    "full_text": "RT @mellythemonkey: i will never give up on you",
    "created_at": "Thu Sep 12 13:27:15 +0000 2013"
  },
  {
    "id": 378147578698661889,
    "user_id": 467503476,
    "full_text": "RT @mellythemonkey: JELIEBERS",
    "created_at": "Thu Sep 12 13:26:23 +0000 2013"
  },
  {
    "id": 378147555122495489,
    "user_id": 467503476,
    "full_text": "RT @mellythemonkey: #believemovie http://t.co/7UMj6ak2dv",
    "created_at": "Thu Sep 12 13:26:17 +0000 2013"
  },
  {
    "id": 376101881447464960,
    "user_id": 467503476,
    "full_text": "RT @mellythemonkey: new album. new songs. new tour",
    "created_at": "Fri Sep 06 21:57:30 +0000 2013"
  },
  {
    "id": 376058147901030400,
    "user_id": 467503476,
    "full_text": "Allergic to stiupid people #stiupid #people #smile #me #selfie #retrica #iphoneonly #summer http://t.co/8RwHHJHmG0",
    "created_at": "Fri Sep 06 19:03:43 +0000 2013"
  },
  {
    "id": 375727959350726656,
    "user_id": 467503476,
    "full_text": "RT @mellythemonkey: Breezy spray painted my half pipe. He's super dope http://t.co/nLT1Qzc6hN",
    "created_at": "Thu Sep 05 21:11:40 +0000 2013"
  },
  {
    "id": 375727741838323712,
    "user_id": 467503476,
    "full_text": "RT @mellythemonkey: im a sexy monkey",
    "created_at": "Thu Sep 05 21:10:49 +0000 2013"
  },
  {
    "id": 375582788956606464,
    "user_id": 467503476,
    "full_text": "RT @mellythemonkey: #lollyvideo #heartbreaker Soon ;)",
    "created_at": "Thu Sep 05 11:34:49 +0000 2013"
  },
  {
    "id": 375582593611075584,
    "user_id": 467503476,
    "full_text": "RT @mellythemonkey: don't tell me you're my heart breaker.",
    "created_at": "Thu Sep 05 11:34:02 +0000 2013"
  },
  {
    "id": 375582080731594752,
    "user_id": 467503476,
    "full_text": "RT @mellythemonkey: #LollyVideo http://t.co/CqOd4C0Lpn",
    "created_at": "Thu Sep 05 11:32:00 +0000 2013"
  },
  {
    "id": 375581668582510592,
    "user_id": 467503476,
    "full_text": "@mellythemonkey Secute ;) @Beyonce",
    "created_at": "Thu Sep 05 11:30:22 +0000 2013"
  },
  {
    "id": 375581157951148032,
    "user_id": 467503476,
    "full_text": "RT @mellythemonkey: she likes to wear my clothes.. #c",
    "created_at": "Thu Sep 05 11:28:20 +0000 2013"
  },
  {
    "id": 373923987904266240,
    "user_id": 467503476,
    "full_text": "RT @jerrybieber_6: WE WILL FIND YOU #DontTouchOurJustin",
    "created_at": "Sat Aug 31 21:43:20 +0000 2013"
  },
  {
    "id": 373923975409434624,
    "user_id": 467503476,
    "full_text": "RT @kidrauh1in: #donttouchourjustin seriously http://t.co/W67LbM8kAm",
    "created_at": "Sat Aug 31 21:43:17 +0000 2013"
  },
  {
    "id": 373923924708712448,
    "user_id": 467503476,
    "full_text": "RT @BelieveInNsn99: #DontTouchOurJustin I'm in tears...he's my idol...YOU CAN'T TOUCH HIM...WHY?!?! HE'S NORMAL...YOU CAN'T",
    "created_at": "Sat Aug 31 21:43:05 +0000 2013"
  },
  {
    "id": 373923776884666368,
    "user_id": 467503476,
    "full_text": "RT @BiebsStyle: #DontTouchOurJustin or http://t.co/8CTLq9qBpr",
    "created_at": "Sat Aug 31 21:42:30 +0000 2013"
  },
  {
    "id": 373923705539551232,
    "user_id": 467503476,
    "full_text": "RT @Julieee_Biieber: #DontTouchOurJustin or http://t.co/x6cepPS1XM",
    "created_at": "Sat Aug 31 21:42:13 +0000 2013"
  },
  {
    "id": 373923629668773888,
    "user_id": 467503476,
    "full_text": "RT @lovebieber9794: I actually stayed after all this. #DontTouchOurJustin  http://t.co/S4PBQYPi4d\"",
    "created_at": "Sat Aug 31 21:41:55 +0000 2013"
  },
  {
    "id": 373922247293300736,
    "user_id": 467503476,
    "full_text": "@justinbieber we love youuuuu 😍 @monikakralj",
    "created_at": "Sat Aug 31 21:36:25 +0000 2013"
  },
  {
    "id": 373922005126758400,
    "user_id": 467503476,
    "full_text": "@monikakralj love you sweetie 😘",
    "created_at": "Sat Aug 31 21:35:27 +0000 2013"
  },
  {
    "id": 373031937704996864,
    "user_id": 467503476,
    "full_text": "RT @godsgirl8494: If your not making someone else's life better, then your wasting your time.",
    "created_at": "Thu Aug 29 10:38:39 +0000 2013"
  },
  {
    "id": 372480919950884864,
    "user_id": 467503476,
    "full_text": "RT @mellythemonkey: u smile i smile",
    "created_at": "Tue Aug 27 22:09:06 +0000 2013"
  },
  {
    "id": 372415665317371904,
    "user_id": 467503476,
    "full_text": "@mellythemonkey i believe he's here and i know he is. Tattoos aren't big problem.. They are cute at some way. Dont judge, thats his body!!",
    "created_at": "Tue Aug 27 17:49:48 +0000 2013"
  },
  {
    "id": 371984886384848896,
    "user_id": 467503476,
    "full_text": "RT @mellythemonkey: ART is everywhere #heARTbreaker",
    "created_at": "Mon Aug 26 13:18:02 +0000 2013"
  },
  {
    "id": 371356216607637504,
    "user_id": 467503476,
    "full_text": "Two bestfriends ❤✌#bf #dog #happy #smile #hair #friends #forever #walk http://t.co/payr9xvRa9",
    "created_at": "Sat Aug 24 19:39:56 +0000 2013"
  },
  {
    "id": 371343609817473024,
    "user_id": 467503476,
    "full_text": "scooter called us justin bieber fans instead of beliebers so how about we call him bicycle instead of scooter http://t.co/9LlOkzD88X",
    "created_at": "Sat Aug 24 18:49:50 +0000 2013"
  },
  {
    "id": 371343352882823168,
    "user_id": 467503476,
    "full_text": "RT @PopCrush: Get ready to scream #Beliebers... @justinbieber \"can't wait\" to have a wife + kids: http://t.co/U2XjPbTEud",
    "created_at": "Sat Aug 24 18:48:49 +0000 2013"
  },
  {
    "id": 371343184020115457,
    "user_id": 467503476,
    "full_text": "RT @NiallOfficial: Guys ! Best song ever is nominated for best song of the summer at the VMA's ! Lets do it! #voteonedirection",
    "created_at": "Sat Aug 24 18:48:08 +0000 2013"
  },
  {
    "id": 371087046527680512,
    "user_id": 467503476,
    "full_text": "I wish I could die right now..",
    "created_at": "Sat Aug 24 01:50:21 +0000 2013"
  },
  {
    "id": 371085745341362176,
    "user_id": 467503476,
    "full_text": "\"Beliebers are not the same anymore... bla bla bla\" OK we're not, no need to rant about it, build a bridge and get over it faggot.",
    "created_at": "Sat Aug 24 01:45:10 +0000 2013"
  },
  {
    "id": 371085141395140608,
    "user_id": 467503476,
    "full_text": "'After storm comes the rainbow...' they sad. But I asking myself when is that. #sad",
    "created_at": "Sat Aug 24 01:42:46 +0000 2013"
  },
  {
    "id": 370586769336844288,
    "user_id": 467503476,
    "full_text": "RT @luke_brooks: Chills on this beautiful sunny day http://t.co/j2jJQET6jh",
    "created_at": "Thu Aug 22 16:42:25 +0000 2013"
  },
  {
    "id": 370586606547525632,
    "user_id": 467503476,
    "full_text": "RT @rauhlthebieber: fuck me tight and don't let go",
    "created_at": "Thu Aug 22 16:41:46 +0000 2013"
  },
  {
    "id": 369888127449849856,
    "user_id": 467503476,
    "full_text": "RT @monikakralj: We love you Justin @LaraIsBelieber @NicoleMcCidden",
    "created_at": "Tue Aug 20 18:26:16 +0000 2013"
  },
  {
    "id": 369091704936071169,
    "user_id": 467503476,
    "full_text": "RT @rossR5: #PassMeBy",
    "created_at": "Sun Aug 18 13:41:34 +0000 2013"
  },
  {
    "id": 369091108527042560,
    "user_id": 467503476,
    "full_text": "RT @rossR5: Damn this song is sexy. haha http://t.co/d6FioEjgw2",
    "created_at": "Sun Aug 18 13:39:12 +0000 2013"
  },
  {
    "id": 369090472104321025,
    "user_id": 467503476,
    "full_text": "When he dance :-)\nhttp://t.co/LhUqrB90vC",
    "created_at": "Sun Aug 18 13:36:40 +0000 2013"
  },
  {
    "id": 368487733733236736,
    "user_id": 467503476,
    "full_text": "nice ass http://t.co/8A5boVzCII\n\n#MTVhottest Justin Bieber",
    "created_at": "Fri Aug 16 21:41:36 +0000 2013"
  },
  {
    "id": 368486930586935296,
    "user_id": 467503476,
    "full_text": "@AlexConstancio7 Go? Haha",
    "created_at": "Fri Aug 16 21:38:25 +0000 2013"
  },
  {
    "id": 368485459288006656,
    "user_id": 467503476,
    "full_text": "Preparing for my lolly music video audition http://t.co/4fzW0HGIat @BieberAudio Yeaah something like that we can expect haha",
    "created_at": "Fri Aug 16 21:32:34 +0000 2013"
  },
  {
    "id": 368484292914991104,
    "user_id": 467503476,
    "full_text": "@Wordsharei258 Yeaaaah no.",
    "created_at": "Fri Aug 16 21:27:56 +0000 2013"
  },
  {
    "id": 368484043177725953,
    "user_id": 467503476,
    "full_text": "@allisimpson I have fml",
    "created_at": "Fri Aug 16 21:26:56 +0000 2013"
  },
  {
    "id": 368483983081762816,
    "user_id": 467503476,
    "full_text": "RT @allisimpson: ain't nobody got time for that",
    "created_at": "Fri Aug 16 21:26:42 +0000 2013"
  },
  {
    "id": 368483903356424192,
    "user_id": 467503476,
    "full_text": "I'd rather see Justin's smile then his abs. Even if they're sexy as hell tough. :)\n #MTVHottest Justin Bieber",
    "created_at": "Fri Aug 16 21:26:23 +0000 2013"
  }
]